CHANGES.txt
README.txt
ZopePublicLicense.txt
bootstrap.py
buildout.cfg
setup.py
src/zope/__init__.py
src/zope.app.wfmc.egg-info/PKG-INFO
src/zope.app.wfmc.egg-info/SOURCES.txt
src/zope.app.wfmc.egg-info/dependency_links.txt
src/zope.app.wfmc.egg-info/namespace_packages.txt
src/zope.app.wfmc.egg-info/not-zip-safe
src/zope.app.wfmc.egg-info/requires.txt
src/zope.app.wfmc.egg-info/top_level.txt
src/zope/app/__init__.py
src/zope/app/wfmc/SETUP.cfg
src/zope/app/wfmc/__init__.py
src/zope/app/wfmc/configure.zcml
src/zope/app/wfmc/meta.zcml
src/zope/app/wfmc/metaconfigure.py
src/zope/app/wfmc/publication.xpdl
src/zope/app/wfmc/tests.py
src/zope/app/wfmc/xpdl2zcml.py
src/zope/app/wfmc/zcml.txt
src/zope/app/wfmc/zope.app.wfmc-configure.zcml
