Metadata-Version: 1.0
Name: zope.app.wfmc
Version: 0.1.2
Summary: Zope Application integration for ``zope.wfmc``
Home-page: http://cheeseshop.python.org/pypi/zope.app.wfmc
Author: Zope Corporation and Contributors
Author-email: zope3-dev@zope.org
License: ZPL 2.1
Keywords: zope3 wfmc xpdl workflow engine zcml
Platform: UNKNOWN
Classifier: Development Status :: 5 - Production/Stable
Classifier: Environment :: Web Environment
Classifier: Intended Audience :: Developers
Classifier: License :: OSI Approved :: Zope Public License
Classifier: Programming Language :: Python
Classifier: Natural Language :: English
Classifier: Operating System :: OS Independent
Classifier: Topic :: Internet :: WWW/HTTP
Classifier: Framework :: Zope3
